Metadata-Version: 1.1
Name: helga-repost
Version: 1.0.2
Summary: tracks links and alerts if reposted
Home-page: UNKNOWN
Author: Justin Caratzas
Author-email: bigjust@lambdaphil.es
License: LICENSE
Keywords: irc bot repost
Platform: UNKNOWN
Classifier: Development Status :: 5 - Production/Stable
Classifier: License :: OSI Approved :: GNU General Public License v3 (GPLv3)
Classifier: Operating System :: OS Independent
Classifier: Programming Language :: Python
Classifier: Topic :: Software Development :: Libraries :: Python Modules
